bmserver/__init__.py
bmserver/cli.py
bmserver/schema.py
bmserver/settings.py
bmserver/utils.py
bmserver/chat/cli.py
bmserver/chat/database.py
bmserver/chat/models.jsonl
bmserver/chat/page.py
bmserver/chat/schema.py
bmserver/chat/utils/benchmark.py
bmserver/chat/utils/client.py
bmserver/chat/utils/hub.py
bmserver/chat/utils/server.py
bmserver-1.0.0.dist-info/METADATA
bmserver-1.0.0.dist-info/WHEEL
bmserver-1.0.0.dist-info/entry_points.txt
bmserver-1.0.0.dist-info/licenses/LICENSE
bmserver-1.0.0.dist-info/RECORD
