Metadata-Version: 2.4
Name: bmserver
Version: 1.0.0
Summary: 简化大模型的权重文件管理、推理服务部署与推理性能测试
Project-URL: Homepage, https://github.com/yansh97/bmserver
Author-email: YanSH <yansh97@foxmail.com>
License: MIT License
License-File: LICENSE
Requires-Python: >=3.12
Requires-Dist: aiohttp>=3.12.13
Requires-Dist: bmhub>=1.0.0
Requires-Dist: numpy>=2.2.6
Requires-Dist: nvidia-ml-py>=12.575.51
Requires-Dist: psycopg[binary,pool]>=3.2.9
Requires-Dist: pydantic-settings>=2.10.1
Requires-Dist: pydantic>=2.11.7
Requires-Dist: python-dotenv>=1.1.1
Requires-Dist: rich>=14.0.0
Requires-Dist: sqlalchemy>=2.0.41
Requires-Dist: typer>=0.16.0
Requires-Dist: vllm==0.8.4
